drime_s3/__init__.py
drime_s3/__main__.py
drime_s3/api.py
drime_s3/gateway.py
drime_s3/models.py
drime_s3-1.0.4.dist-info/METADATA
drime_s3-1.0.4.dist-info/WHEEL
drime_s3-1.0.4.dist-info/entry_points.txt
drime_s3-1.0.4.dist-info/top_level.txt
drime_s3-1.0.4.dist-info/RECORD
