Metadata-Version: 2.4
Name: drime-s3
Version: 1.0.4
Summary: S3-compatible gateway for Drime Cloud
Author-email: JD <diego.juan@gmail.com>
License: MIT
Project-URL: Homepage, https://github.com/diegojuan/drime-s3
Keywords: s3,drime,cloud,storage,gateway
Classifier: Development Status :: 4 - Beta
Classifier: Intended Audience :: Developers
Classifier: License :: OSI Approved :: MIT License
Classifier: Programming Language :: Python :: 3
Classifier: Programming Language :: Python :: 3.10
Classifier: Programming Language :: Python :: 3.11
Classifier: Programming Language :: Python :: 3.12
Requires-Python: >=3.10
Requires-Dist: httpx>=0.25.0
Requires-Dist: cheroot>=10.0.0
